{
  "quiz": {
    "title": "Квіз на вивчення букви Н",
    "description": "Квіз для перевірки знань про букву Н",
    "version": "1.0",
    "questions": [
      {
        "id": 1,
        "question": "Яке слово починається на букву \"Н\"?",
        "options": [
          {"id": 0, "text": "Книга"},
          {"id": 1, "text": "Небо"},
          {"id": 2, "text": "Дім"}
        ],
        "correctAnswerId": 1
      },
      {
        "id": 2,
        "question": "Яка тварина починається на літеру \"Н\"?",
        "options": [
          {"id": 0, "text": "Носоріг"},
          {"id": 1, "text": "Єнот"},
          {"id": 2, "text": "Ведмідь"}
        ],
        "correctAnswerId": 0
      },
      {
        "id": 3,
        "question": "Яке слово НЕ містить букву \"Н\"?",
        "options": [
          {"id": 0, "text": "Ніч"},
          {"id": 1, "text": "Книга"},
          {"id": 2, "text": "Дощ"}
        ],
        "correctAnswerId": 2
      },
      {
        "id": 4,
        "question": "Яке місто України починається на літеру \"Н\"?",
        "options": [
          {"id": 0, "text": "Ніжин"},
          {"id": 1, "text": "Харків"},
          {"id": 2, "text": "Одеса"}
        ],
        "correctAnswerId": 0
      },
      {
        "id": 5,
        "question": "Яке з цих слів має склад \"НО\"?",
        "options": [
          {"id": 0, "text": "Новий"},
          {"id": 1, "text": "Нива"},
          {"id": 2, "text": "Небо"}
        ],
        "correctAnswerId": 0
      },
      {
        "id": 6,
        "question": "Яка професія починається на літеру \"Н\"?",
        "options": [
          {"id": 0, "text": "Науковець"},
          {"id": 1, "text": "Вчитель"},
          {"id": 2, "text": "Лікар"}
        ],
        "correctAnswerId": 0
      },
      {
        "id": 7,
        "question": "Що можна їсти на букву \"Н\"?",
        "options": [
          {"id": 0, "text": "Нектарин"},
          {"id": 1, "text": "Яблуко"},
          {"id": 2, "text": "Груша"}
        ],
        "correctAnswerId": 0
      },
      {
        "id": 8,
        "question": "Який напій починається на літеру \"Н\"?",
        "options": [
          {"id": 0, "text": "Нектар"},
          {"id": 1, "text": "Сік"},
          {"id": 2, "text": "Вода"}
        ],
        "correctAnswerId": 0
      },
      {
        "id": 9,
        "question": "Яке жіноче ім'я починається на літеру \"Н\"?",
        "options": [
          {"id": 0, "text": "Наталія"},
          {"id": 1, "text": "Марія"},
          {"id": 2, "text": "Ольга"}
        ],
        "correctAnswerId": 0
      },
      {
        "id": 10,
        "question": "Яка частина тіла починається на літеру \"Н\"?",
        "options": [
          {"id": 0, "text": "Нога"},
          {"id": 1, "text": "Рука"},
          {"id": 2, "text": "Голова"}
        ],
        "correctAnswerId": 0
      }
    ]
  }
}